aeslibrarysi/AES.py
aeslibrarysi/AESParameters.py
aeslibrarysi/__init__.py
aeslibrarysi/diffie_server_utils.py
aeslibrarysi/utils.py
aeslibrarysi-0.1.dist-info/METADATA
aeslibrarysi-0.1.dist-info/WHEEL
aeslibrarysi-0.1.dist-info/top_level.txt
aeslibrarysi-0.1.dist-info/RECORD
