Metadata-Version: 2.1
Name: aeslibrarysi
Version: 0.1
Summary: A personalised Python library for encrypt messages with aes.
Author: Pasa Larisa
